certbot_dns_zoneedit.py
zoneedit.ini
certbot_dns_zoneedit-0.3.2.dist-info/LICENSE.txt
certbot_dns_zoneedit-0.3.2.dist-info/METADATA
certbot_dns_zoneedit-0.3.2.dist-info/WHEEL
certbot_dns_zoneedit-0.3.2.dist-info/entry_points.txt
certbot_dns_zoneedit-0.3.2.dist-info/RECORD
