Metadata-Version: 2.1
Name: certbot-dns-zoneedit
Version: 0.3.2
Summary: A Certbot plugin that implements LetsEncrypt DNS-01 challenge via ZoneEdit
Home-page: https://github.com/zlaski/certbot-dns-zoneedit
License: Apache-2.0
Author: Ziemowit Łąski
Author-email: zlaski@ziemas.net
Requires-Python: >=3.7,<4.0
Classifier: Development Status :: 3 - Alpha
Classifier: Environment :: Plugins
Classifier: Intended Audience :: System Administrators
Classifier: License :: OSI Approved :: Apache Software License
Classifier: Operating System :: OS Independent
Classifier: Programming Language :: Python :: 3
Classifier: Programming Language :: Python :: 3.7
Classifier: Programming Language :: Python :: 3.8
Classifier: Programming Language :: Python :: 3.9
Classifier: Programming Language :: Python :: 3.10
Classifier: Programming Language :: Python :: 3.11
Classifier: Programming Language :: Python :: 3 :: Only
Classifier: Topic :: Internet :: WWW/HTTP
Classifier: Topic :: Security
Classifier: Topic :: System :: Installation/Setup
Classifier: Topic :: System :: Networking
Classifier: Topic :: System :: Systems Administration
Classifier: Topic :: Utilities
Requires-Dist: acme (>=2.4.0)
Requires-Dist: certbot (>=2.4.0)
Requires-Dist: dnspython (>=2.3.0)
Requires-Dist: logging (>=0.4.9)
Requires-Dist: requests (>=2.31.0)
Project-URL: Repository, https://github.com/zlaski/certbot-dns-zoneedit
